cflapi/__init__.py
cflapi/cflapi.py
cflapi/utils.py
cflapi-1.0.2.dist-info/METADATA
cflapi-1.0.2.dist-info/RECORD
cflapi-1.0.2.dist-info/WHEEL
cflapi-1.0.2.dist-info/top_level.txt
test/__init__.py
test/test_cflapi.py
test/test_cflapi_games.py
test/test_cflapi_players.py
