Metadata-Version: 2.1
Name: cflapi
Version: 1.0.2
Summary: Canadian Football League API Wrapper
Home-page: https://github.com/streibeb/cflapi
Author: Brayden Streibel
Author-email: brayden@streibel.ca
License: MIT
Platform: UNKNOWN
Classifier: Programming Language :: Python :: 3
Classifier: Programming Language :: Python :: 3.6
Classifier: License :: OSI Approved :: MIT License
Classifier: Operating System :: OS Independent
Requires-Dist: requests
